dlisio-1.0.3.dist-info/RECORD
dlisio-1.0.3.dist-info/METADATA
dlisio-1.0.3.dist-info/WHEEL
dlisio-1.0.3.dist-info/top_level.txt
dlisio/__init__.py
dlisio/core.cpython-39-x86_64-linux-gnu.so
dlisio/dlis/wellref.py
dlisio/dlis/coefficient.py
dlisio/dlis/origin.py
dlisio/dlis/fileheader.py
dlisio/dlis/noformat.py
dlisio/dlis/channel.py
dlisio/dlis/comment.py
dlisio/dlis/message.py
dlisio/dlis/unknown.py
dlisio/dlis/path.py
dlisio/dlis/parameter.py
dlisio/dlis/basicobject.py
dlisio/dlis/frame.py
dlisio/dlis/calibration.py
dlisio/dlis/process.py
dlisio/dlis/load.py
dlisio/dlis/group.py
dlisio/dlis/__init__.py
dlisio/dlis/axis.py
dlisio/dlis/computation.py
dlisio/dlis/tool.py
dlisio/dlis/zone.py
dlisio/dlis/measurement.py
dlisio/dlis/longname.py
dlisio/dlis/file.py
dlisio/dlis/equipment.py
dlisio/dlis/splice.py
dlisio/dlis/utils/fdata.py
dlisio/dlis/utils/matcher.py
dlisio/dlis/utils/reprc.py
dlisio/dlis/utils/__init__.py
dlisio/dlis/utils/valuetypes.py
dlisio/dlis/utils/linkage.py
dlisio/dlis/utils/describe.py
dlisio/dlis/utils/dimensional.py
dlisio/lis/dataformatspec.py
dlisio/lis/load.py
dlisio/lis/__init__.py
dlisio/lis/information_record.py
dlisio/lis/file.py
dlisio/lis/curves.py
dlisio/common/__init__.py
dlisio/common/errorhandler.py
dlisio/common/open.py
dlisio/common/settings.py
