Metadata-Version: 2.2
Name: dlisio
Version: 1.0.3
Summary: Python library for working with the well log formats DLIS (RP66v1) and LIS79
Home-page: https://github.com/equinor/dlisio
License: LGPL-3.0
Platform: any
Requires-Dist: numpy
Dynamic: description
Dynamic: description-content-type
Dynamic: home-page
Dynamic: license
Dynamic: platform
Dynamic: requires-dist
Dynamic: summary
